{
    "description": "Seasonal weapons, based on various website suggested rolls first week of the season",
    "name": "S22",
    "data": [
        {
            "description": "",
            "hash": 2779821308,
            "name": "",
            "plugs": [
                [
                    839105230
                ],
                [
                    106909392
                ],
                [
                    247725512,
                    3700496672,
                    2938480696,
                    2840833776
                ],
                [
                    3038247973,
                    555281244,
                    64866129,
                    332733060
                ]
            ],
            "tags": [
                "PVE"
            ]
        },
        {
            "description": "",
            "hash": 2779821308,
            "name": "",
            "plugs": [
                [
                    3250034553,
                    1482024992
                ],
                [
                    3142289711,
                    3177308360
                ],
                [
                    3619207468,
                    247725512,
                    3198323828,
                    2938480696
                ],
                [
                    555281244,
                    3038247973,
                    3673922083,
                    332733060,
                    64866129,
                    2889515627
                ]
            ],
            "tags": [
                "PVP"
            ]
        },
        {
            "description": "",
            "hash": 105306149,
            "name": "",
            "plugs": [
                [
                    839105230
                ],
                [
                    1087426260
                ],
                [
                    2387244414,
                    1748774930
                ],
                [
                    365154968,
                    2939589096
                ]
            ],
            "tags": [
                "PVE"
            ]
        },
        {
            "description": "",
            "hash": 105306149,
            "name": "",
            "plugs": [
                [
                    3250034553
                ],
                [
                    1885400500
                ],
                [
                    588594999,
                    2717805783
                ],
                [
                    1890422124,
                    1523649716
                ]
            ],
            "tags": [
                "PVP"
            ]
        },
        {
            "description": "",
            "hash": 3347946548,
            "name": "",
            "plugs": [
                [
                    839105230
                ],
                [
                    1687452232,
                    689005463
                ],
                [
                    1556840489,
                    3017780555,
                    968510818,
                    3442762221,
                    4223976499,
                    424370782
                ],
                [
                    1427256713,
                    2594592626,
                    254337357,
                    2037312142
                ]
            ],
            "tags": [
                "PVE"
            ]
        },
        {
            "description": "",
            "hash": 1875512595,
            "name": "",
            "plugs": [
                [
                    3250034553,
                    1392496348
                ],
                [
                    3142289711
                ],
                [
                    706527188,
                    1961144892,
                    2450788523,
                    4207509907
                ],
                [
                    699525795,
                    3719974635,
                    2458213969,
                    2570477205
                ]
            ],
            "tags": [
                "PVP"
            ]
        },
        {
            "description": "",
            "hash": 1875512595,
            "name": "",
            "plugs": [
                [
                    1392496348
                ],
                [
                    2420895100
                ],
                [
                    1119449540,
                    561986700
                ],
                [
                    3324494224,
                    2562668800
                ]
            ],
            "tags": [
                "PVE"
            ]
        },
        {
            "description": "",
            "hash": 4132072834,
            "name": "",
            "plugs": [
                [
                    839105230
                ],
                [
                    3142289711
                ],
                [
                    3643424744,
                    2682205016
                ],
                [
                    2319119708,
                    2140591236,
                    47981717,
                    1370847713,
                    124408337,
                    1171887445
                ]
            ],
            "tags": [
                "PVE",
                "PVP"
            ]
        },
        {
            "description": "",
            "hash": 2922749929,
            "name": "",
            "plugs": [
                [
                    3525010810
                ],
                [
                    3796465595,
                    1996142143
                ],
                [
                    2869569095,
                    2308090567
                ],
                [
                    3194351027,
                    2275087323
                ]
            ],
            "tags": [
                "PVE"
            ]
        },
        {
            "description": "",
            "hash": 2922749929,
            "name": "",
            "plugs": [
                [
                    3525010810
                ],
                [
                    2822142346
                ],
                [
                    951095735,
                    3878366039
                ],
                [
                    960810156,
                    1077019636
                ]
            ],
            "tags": [
                "PVP"
            ]
        },
        {
            "description": "",
            "hash": 3637669759,
            "name": "",
            "plugs": [
                [
                    3666208348
                ],
                [
                    269888150
                ],
                [
                    1749209109
                ],
                [
                    3913600130
                ]
            ],
            "tags": [
                "PVE"
            ]
        },
        {
            "description": "",
            "hash": 3637669759,
            "name": "",
            "plugs": [
                [
                    436053704
                ],
                [
                    52780822
                ],
                [
                    776531651
                ],
                [
                    2048641572
                ]
            ],
            "tags": [
                "PVE"
            ]
        },
        {
            "description": "",
            "hash": 358788212,
            "name": "",
            "plugs": [
                [
                    839105230
                ],
                [
                    3230963543,
                    3142289711
                ],
                [
                    3828510309,
                    1168162263,
                    1195158366
                ],
                [
                    124408337,
                    1015611457,
                    460017080
                ]
            ],
            "tags": [
                "PVE"
            ]
        },
        {
            "description": "",
            "hash": 3998080529,
            "name": "",
            "plugs": [
                [
                    3250034553,
                    839105230
                ],
                [
                    3230963543
                ],
                [
                    3828510309,
                    3017780555
                ],
                [
                    3708227201,
                    1015611457,
                    4293542123
                ]
            ],
            "tags": [
                "PVE"
            ]
        },
        {
            "description": "",
            "hash": 3998080529,
            "name": "",
            "plugs": [
                [
                    3250034553,
                    839105230
                ],
                [
                    3142289711
                ],
                [
                    1428297954,
                    588594999
                ],
                [
                    1015611457
                ]
            ],
            "tags": [
                "PVP"
            ]
        },
        {
            "description": "",
            "hash": 2767393525,
            "name": "",
            "plugs": [
                [
                    839105230
                ],
                [
                    1687452232
                ],
                [
                    1119449540,
                    1556840489
                ],
                [
                    831391274,
                    2594592626
                ]
            ],
            "tags": [
                "PVE"
            ]
        },
        {
            "description": "",
            "hash": 2767393525,
            "name": "",
            "plugs": [
                [
                    3250034553
                ],
                [
                    2969185026
                ],
                [
                    4071163871
                ],
                [
                    1754714824,
                    3511092054,
                    2594592626
                ]
            ],
            "tags": [
                "PVP"
            ]
        }
    ]
}